genpull/__about__.py
genpull/__init__.py
genpull/__main__.py
genpull/cli.py
genpull/gpull.py
genpull/tex_escape.py
genpull/templates/subscriptions.jinja
genpull-1.4.dist-info/METADATA
genpull-1.4.dist-info/WHEEL
genpull-1.4.dist-info/entry_points.txt
genpull-1.4.dist-info/licenses/LICENSE
genpull-1.4.dist-info/RECORD
