Metadata-Version: 2.4
Name: genpull
Version: 1.4
Summary: CLI for generating a LaTeX file based upon your League of Comic Geeks exported pulls.
Project-URL: Homepage, https://github.com/devnevins/genpull
Project-URL: Issues, https://github.com/devnevins/genpull/issues
Author-email: Dean Nevins <pypicontact.living477@passmail.com>
License-Expression: MIT
License-File: LICENSE
Keywords: comic geeks,comics,locg
Classifier: License :: OSI Approved :: MIT License
Classifier: Programming Language :: Python :: 3.12
Requires-Python: >=3.12
Requires-Dist: jinja2>3.0.0
Requires-Dist: typer>0.15
Requires-Dist: xlrd>=2.0.1
